[{"topic":"پاداش","subtopic":"پاداش پرهيزگاران","desc":"تضمين پيروزى پرهيزگاران ازسوى خداوند","sura":9,"aya":36},{"topic":"پاداش","subtopic":"پاداش پرهيزگاران","desc":"بهشت دلپذير پاداش موعود مومنان پرهيزگار","sura":38,"aya":54},{"topic":"پاداش","subtopic":"پاداش پرهيزگاران","desc":"بهشت، پاداش اعمال پرهيزگاران","sura":43,"aya":72},{"topic":"پاداش","subtopic":"پاداش پرهيزگاران","desc":"دريافت مواهب الهي از سوى پرهيزگاران به پاداش نيكوكارى آنها","sura":51,"aya":16},{"topic":"پاداش","subtopic":"پاداش پرهيزگاران","desc":"كاسته نشدن پاداش عمل پرهيزگاران درقبال ترفيع درجه فرزندان آنان در بهشت","sura":52,"aya":21},{"topic":"پاداش","subtopic":"پاداش پرهيزگارى","desc":"وعده بهشت ازسوى خدا براى پرهيزگاران","sura":47,"aya":15},{"topic":"پاداش","subtopic":"پاداش پس از آزمون","desc":"جزاء نيكوى خداوند پس از امتحانهاى نيكوكاران","sura":37,"aya":105},{"topic":"پاداش","subtopic":"پاداش پس از آزمون","desc":"پاسخ و پاداش نيكوى خداوند به نيكوكاران پس از موفقيت در امتحانات الهي","sura":37,"aya":110},{"topic":"پاداش","subtopic":"پاداش پيامبر","desc":"تعلق پاداش عظيم ازسوى خداى سبحان به پيامبر اكرم بپاس خدمات او","sura":68,"aya":3},{"topic":"پاداش","subtopic":"پاداش پيامبران","desc":"پاداش پيامبران بر عهده خدا","sura":10,"aya":72},{"topic":"پاداش","subtopic":"پاداش پيامبران","desc":"اعطاى پاداش رسالت به پيامبران ازسوى خداوند","sura":11,"aya":51},{"topic":"پاداش","subtopic":"پاداش پيامبران","desc":"برخوردارى پيامبران و مؤمنان از رحمت الهي در دنيا","sura":11,"aya":58},{"topic":"پاداش","subtopic":"پاداش پيامبران","desc":"برخوردارى پيامبران از رحمت خاص الهي","sura":11,"aya":63},{"topic":"پاداش","subtopic":"پاداش پيامبران","desc":"برخوردارى پيامبران و مؤمنان از رحمت الهي","sura":11,"aya":66},{"topic":"پاداش","subtopic":"پاداش پيامبران","desc":"برخوردارى مؤمنان و پيامبران از رحمت الهي در دنيا","sura":11,"aya":94},{"topic":"پاداش","subtopic":"پاداش پيامبران","desc":"مطالبه نكردن اجر و مزد، دليل صداقت و حقانيت پيامبران","sura":12,"aya":104},{"topic":"پاداش","subtopic":"پاداش تسليم","desc":"پاداش تسليم كامل دربرابر خداوند و انجام اعمال نيک","sura":2,"aya":112},{"topic":"پاداش","subtopic":"پاداش جنگ","desc":"تفاوت مسلمانان و دشمنانشان در پاداش و كيفر جنگ","sura":4,"aya":104},{"topic":"پاداش","subtopic":"پاداش جهاد","desc":"اختصاص پاداش جهاد به مجاهدان نيكوكار و پرهيزگار","sura":3,"aya":172},{"topic":"پاداش","subtopic":"پاداش جهاد","desc":"پاداش بزرگ و گرانقدر جهاد مخلصانه در راه خدا","sura":3,"aya":172},{"topic":"پاداش","subtopic":"پاداش جهاد","desc":"اهميت جهاد در راه خدا و پاداش بزرگ آن","sura":4,"aya":95},{"topic":"پاداش","subtopic":"پاداش جهاد","desc":"آمرزش گناهان مجاهدان و نزول رحمت الهي بر آنان","sura":4,"aya":96},{"topic":"پاداش","subtopic":"پاداش جهاد","desc":"ارزش و پاداش بزرگ جهاد جاني و مالي در راه خدا","sura":9,"aya":20},{"topic":"پاداش","subtopic":"پاداش جهاد","desc":"برخوردارى مؤمنان مهاجر و مجاهد از رحمت و خشنودى خداوند","sura":9,"aya":21},{"topic":"پاداش","subtopic":"پاداش جهاد","desc":"برخوردارى مؤمنان مهاجر و مجاهد از نعمتهاى جاودان در باغهاى بهشت","sura":9,"aya":21},{"topic":"پاداش","subtopic":"پاداش جهاد","desc":"پاداش بهشت در ازاى جهاد در راه خدا","sura":9,"aya":111},{"topic":"پاداش","subtopic":"پاداش جهاد","desc":"برترى و بزرگي پاداش جهاد نسبت به خود آن","sura":9,"aya":121},{"topic":"پاداش","subtopic":"پاداش جهاد","desc":"بخشش گناهان و ورود به باغهاى باصفاى بهشت، پاداش جهاد در راه خدا با مال و جان","sura":61,"aya":12},{"topic":"پاداش","subtopic":"پاداش حق طلبي","desc":"پاداش بيشمار براى آدمي درپي پايدارى در راه حق و تحمل دشواريها","sura":39,"aya":10},{"topic":"پاداش","subtopic":"پاداش خانه نشين","desc":"افزون بودن پاداش مجاهدان بر پاداش خانه‌نشينان","sura":4,"aya":95},{"topic":"پاداش","subtopic":"پاداش خدا","desc":"تضمين پاداش الهي براى همه اعمال نيک","sura":2,"aya":158},{"topic":"پاداش","subtopic":"پاداش خدا","desc":"پاداش عظيم خداوند براى مؤمنان پرهيزگار","sura":3,"aya":179},{"topic":"پاداش","subtopic":"پاداش خدا","desc":"ترغيب به‌سوى اعمال نيک ازطريق توجه به پاداش الهي آن","sura":4,"aya":40},{"topic":"پاداش","subtopic":"پاداش خدا","desc":"خداوند، مالک پاداش و نعمتهاى دنيوى و اخروى","sura":4,"aya":134},{"topic":"پاداش","subtopic":"پاداش خدا","desc":"عدالت خداوند در اداى پاداش اعمال بنحو كامل","sura":8,"aya":60},{"topic":"پاداش","subtopic":"پاداش خدا","desc":"بزرگي پاداش خداوند","sura":9,"aya":22},{"topic":"پاداش","subtopic":"پاداش خدا","desc":"معيار قراردادن بهترين فرد اعمال و محاسبه پاداش همه اعمال بر اساس آن","sura":16,"aya":96},{"topic":"پاداش","subtopic":"پاداش خدا","desc":"كيفر و پاداش و نصرت خداوند به اقتضاء حقانيت و وايي و عظمت او","sura":22,"aya":62},{"topic":"پاداش","subtopic":"پاداش خدا","desc":"مشروط بودن فضل و پاداش الهي به مشيت حضرت حق","sura":57,"aya":29},{"topic":"پاداش","subtopic":"پاداش خدا","desc":"جزاى عادنه خداوند به مردم  براساس علم و اطلاع او از اعمال و نيات آدمي","sura":100,"aya":10},{"topic":"پاداش","subtopic":"پاداش خداوند","desc":"پاداش و كرامت خداوند به انفاق كنندگان در راه او","sura":35,"aya":30},{"topic":"پاداش","subtopic":"پاداش خضوع","desc":"خلود مؤمنان صالح و خاضع در بهشت","sura":11,"aya":23},{"topic":"پاداش","subtopic":"پاداش خوبان","desc":"بهشت ابدى با تمامي گوهرهايش، پاداش خوبان","sura":35,"aya":33},{"topic":"پاداش","subtopic":"پاداش خوبي","desc":"برابرى جزاء بدى با بدى و افزايش بي‌حد و حصر پاداش خوبي بر خوبي","sura":40,"aya":40},{"topic":"پاداش","subtopic":"پاداش خيرات","desc":"پاداش نيكوى خداوند در ازاء سبقت در انجام خيرات","sura":35,"aya":32},{"topic":"پاداش","subtopic":"پاداش در آخرت","desc":"ضرورت تكرار عمل نيكو براى رسوخ در جان و پاداش نيكو در آخرت","sura":39,"aya":35},{"topic":"پاداش","subtopic":"پاداش در رستاخيز","desc":"كيفر و پاداش همگان در روز رستاخيز","sura":14,"aya":51},{"topic":"پاداش","subtopic":"پاداش در قيامت","desc":"تحقق عدالت در پاداش و جزا بعنوان هدف معاد","sura":10,"aya":4},{"topic":"پاداش","subtopic":"پاداش درستكارى","desc":"ارزش راستگويي و درستكارى و پاداش آن در آخرت","sura":4,"aya":69},{"topic":"پاداش","subtopic":"پاداش دنياطلبي","desc":"دستيابي دنياطلبان به بهره‌ها و منافع دنيوى","sura":3,"aya":145},{"topic":"پاداش","subtopic":"پاداش دنيوى","desc":"اعطاء پاداش به مجاهدان در راه خداوند در دنيا و آخرت","sura":3,"aya":148},{"topic":"پاداش","subtopic":"پاداش دنيوى","desc":"برترى پاداش اخروى بر پاداش دنيوى","sura":3,"aya":148},{"topic":"پاداش","subtopic":"پاداش دنيوى","desc":"جايي نيكو در دنيا و پاداشي بزرگ در آخرت براى  ستمديدگان مهاجر در راه خدا","sura":16,"aya":41},{"topic":"پاداش","subtopic":"پاداش دينداران","desc":"پوشاندن بديها و پاداش خوبيهاى پيروان شريعت درپرتو عنايات خداوند","sura":39,"aya":35},{"topic":"پاداش","subtopic":"پاداش راستگويي","desc":"ارزش راستگويي و درستكارى و پاداش آن در آخرت","sura":4,"aya":69},{"topic":"پاداش","subtopic":"پاداش رسالت","desc":"عدم درخواست اجرت و پاداش رسالت از مردم","sura":6,"aya":90},{"topic":"پاداش","subtopic":"پاداش رسالت","desc":"اعطاى پاداش رسالت و نبوت ازسوى خداوند","sura":11,"aya":29},{"topic":"پاداش","subtopic":"پاداش رسالت","desc":"توقع نداشتن پيامبر هيچگونه پاداش از مردم درقبال ابلاغ رسالت","sura":52,"aya":40},{"topic":"پاداش","subtopic":"پاداش رستگاران","desc":"سنت الهي در كيفر و پاداش انسانها درقبال اعمال آنان","sura":85,"aya":11},{"topic":"پاداش","subtopic":"پاداش زكات","desc":"پاداش برپاداشتن نماز و پرداختن زكات","sura":2,"aya":277},{"topic":"پاداش","subtopic":"پاداش زن","desc":"برابرى زن و مرد در دريافت پاداش عمل","sura":3,"aya":195},{"topic":"پاداش","subtopic":"پاداش زنان","desc":"ضمانت پاداش اعمال زنان و مردان ازسوى خداوند","sura":3,"aya":195},{"topic":"پاداش","subtopic":"پاداش زنان","desc":"بهره‌مندى زنان و مردان از نتايج اعمال و امكانات خود","sura":4,"aya":32},{"topic":"پاداش","subtopic":"پاداش سپاسگزاران","desc":"پاداش نيک خداوند براى سپاسگزاران","sura":3,"aya":144},{"topic":"پاداش","subtopic":"پاداش سپاسگزاران","desc":"خداوند، ضامن پاداش سپاسگزاران","sura":3,"aya":145},{"topic":"پاداش","subtopic":"پاداش شكيبائي","desc":"پاداش نيک شكيباياني كه عفو را بر انتقام ترجيح مي‌دهند","sura":16,"aya":126},{"topic":"پاداش","subtopic":"پاداش شهادت","desc":"آمرزش و رحمت الهي، پاداش مرگ يا شهادت در راه خداوند","sura":3,"aya":157},{"topic":"پاداش","subtopic":"پاداش شهادت","desc":"نقش توجه به پاداش شهادت در رغبت انسان به جهاد در راه خداوند","sura":3,"aya":157},{"topic":"پاداش","subtopic":"پاداش شهداء","desc":"پاداش بزرگ خداوند به پيروزمندان و شهيدان صحنه‌هاى نبرد و جهاد","sura":4,"aya":74},{"topic":"پاداش","subtopic":"پاداش شهيدان","desc":"برترى پاداش شهدا و مجاهدان در راه خدا بر بهره‌هاى دنيوى ديگران","sura":3,"aya":157},{"topic":"پاداش","subtopic":"پاداش صابران","desc":"برخوردارى صابران و نيكوكاران از مغفرت و پاداش بزرگ خداوند","sura":11,"aya":11},{"topic":"پاداش","subtopic":"پاداش صابران","desc":"تضمين پاداش پارسايان و صابران از سوى خداوند","sura":12,"aya":90},{"topic":"پاداش","subtopic":"پاداش صبر","desc":"شكيبائي بني‌اسرائيل و برخوردارى آنان از پاداش الهي","sura":7,"aya":137},{"topic":"پاداش","subtopic":"پاداش صبر","desc":"تضمين پاداش صبر و نيكوكارى از سوى خداوند","sura":11,"aya":115},{"topic":"پاداش","subtopic":"پاداش صدق","desc":"پاداش خداوند به مومنان صادق به علت صدقشان","sura":33,"aya":24},{"topic":"پاداش","subtopic":"پاداش صدقه","desc":"پاداش خداوند به صدقه‌دهندگان و انفاق كنندگان","sura":12,"aya":88},{"topic":"پاداش","subtopic":"پاداش صدقه","desc":"فزوني اجر و پاداش صدقه دادن و احسان در راه خدا در دنيا و قيامت","sura":57,"aya":18},{"topic":"پاداش","subtopic":"پاداش عاملان","desc":"نيكويي پاداش عاملان","sura":29,"aya":58},{"topic":"پاداش","subtopic":"پاداش عمل","desc":"ضايع نشدن پاداش اعمال شايسته انسان","sura":2,"aya":110},{"topic":"پاداش","subtopic":"پاداش عمل","desc":"برابرى زن و مرد در دريافت پاداش عمل","sura":3,"aya":195},{"topic":"پاداش","subtopic":"پاداش عمل","desc":"نقش ايمان و عمل صالح در رستگارى و شادكامي","sura":6,"aya":48},{"topic":"پاداش","subtopic":"پاداش عمل","desc":"عدالت خداوند در اداى پاداش اعمال بنحو كامل","sura":8,"aya":60},{"topic":"پاداش","subtopic":"پاداش عمل","desc":"اطمينان نيكوكرداران مؤمن از دريافت كامل پاداش اعمالشان در قيامت","sura":20,"aya":112},{"topic":"پاداش","subtopic":"پاداش عمل","desc":"ضايع نشدن عمل و پاداش عمل و ثبت آن در كتابي درنزد خداوند","sura":23,"aya":62},{"topic":"پاداش","subtopic":"پاداش عمل","desc":"پاداش نيكوى ايمان و عمل صالح و كيفر","sura":35,"aya":7},{"topic":"پاداش","subtopic":"پاداش عمل","desc":"بهشت و جهنم پاداش عمل نيكوكاران و بدكاران","sura":42,"aya":7},{"topic":"پاداش","subtopic":"پاداش عمل","desc":"افزايش اجر عمل مؤمنان صالح با فضل خداوند","sura":42,"aya":26},{"topic":"پاداش","subtopic":"پاداش عمل","desc":"عدالت خداوند در كيفر و پاداش عمل نيک و بد انسان","sura":46,"aya":19},{"topic":"پاداش","subtopic":"پاداش عمل","desc":"نقش اطاعت از خدا و رسول در رسيدن انسان به پاداش عمل خود","sura":49,"aya":14},{"topic":"پاداش","subtopic":"پاداش عمل","desc":"دريافت مواهب الهي از سوى پرهيزگاران به پاداش نيكوكارى آنها","sura":51,"aya":16},{"topic":"پاداش","subtopic":"پاداش عمل","desc":"تجسم اعمال نيک و بد انسان در قيامت بصورت نعمت و عذاب","sura":52,"aya":16},{"topic":"پاداش","subtopic":"پاداش عمل","desc":"كاسته نشدن پاداش عمل پرهيزگاران درقبال ترفيع درجه فرزندان آنان در بهشت","sura":52,"aya":21},{"topic":"پاداش","subtopic":"پاداش عمل","desc":"قدرت خداوند در پاداش و كيفر انسانها درقبال عملكرد آنان","sura":53,"aya":31},{"topic":"پاداش","subtopic":"پاداش عمل","desc":"رسيدن انسان به پاداش و كيفر كامل اعمال خود در آخرت","sura":53,"aya":41},{"topic":"پاداش","subtopic":"پاداش عمل","desc":"احسان و نيكي خداوند به بندگان درمقابل اعمال نيک آنان در دنيا","sura":55,"aya":60},{"topic":"پاداش","subtopic":"پاداش عمل","desc":"بهشت، پاداش اعمال نيكوكاران","sura":55,"aya":60},{"topic":"پاداش","subtopic":"پاداش عمل","desc":"عدالت خداوند در كيفر و پاداش شايسته مؤمنان و كافران در روز جزا","sura":68,"aya":35},{"topic":"پاداش","subtopic":"پاداش عمل","desc":"عدالت خداوند در پاداش و كيفر انسان براساس عمل او","sura":78,"aya":26},{"topic":"پاداش","subtopic":"پاداش عمل","desc":"توازن پاداش و كيفرالهي با ميزان عمل آدمي در قيامت","sura":101,"aya":6},{"topic":"پاداش","subtopic":"پاداش فراوان","desc":"پاداش گسترده و فراوان انفاق كنندگان","sura":2,"aya":261}]