[{"topic":"خداوند","subtopic":"گفتگو درباره خداوند","desc":"ضرورت شنيدن اوصاف خداوند از بندگان پاک و صافي","sura":37,"aya":159},{"topic":"خداوند","subtopic":"گفتگو درباره خداوند","desc":"ضرورت شنيدن اوصاف خداوند از بندگان پاک و صافي","sura":37,"aya":160},{"topic":"خداوند","subtopic":"گفتگوى خداوند","desc":"گفتگوى خداوند با فرشتگان درباره استقرار خليفه او در زمين","sura":2,"aya":30},{"topic":"خداوند","subtopic":"گمراه شده خداوند","desc":"بي بهره بودن ابدى كسي‌كه خدايش گمراهش سازد از مرشد","sura":18,"aya":17},{"topic":"خداوند","subtopic":"گنجينه هاى خداوند","desc":"عدم مالكيت پيامبر بر گنجينه‌هاى خداوند","sura":6,"aya":50},{"topic":"خداوند","subtopic":"گواه بودن خداوند","desc":"گواه بودن خداوند بر تمامي امور","sura":33,"aya":55},{"topic":"خداوند","subtopic":"گواهي خداوند","desc":"كفايت گواهي خداوند و عالمان به كتاب بر رسالت پيامبر","sura":13,"aya":43},{"topic":"خداوند","subtopic":"گواهي خداوند","desc":"ماموريت پيامبر در تهديد مشركان به آگاهي خداوند از حال بندگان و گواه بودن او","sura":17,"aya":96},{"topic":"خداوند","subtopic":"گواهي خداوند","desc":"گواهي و حضور خداوند در تمام اشيا و افعال","sura":41,"aya":53},{"topic":"خداوند","subtopic":"لشكرهاى خداوند","desc":"لشكرهاى غيبي خداوند براى پيروزى مؤمنان بر كفار","sura":33,"aya":9},{"topic":"خداوند","subtopic":"لطف خداوند","desc":"لطف خداوند در بيان نكردن برخي از دستورات براى آسايش بيشتر مردم","sura":5,"aya":101},{"topic":"خداوند","subtopic":"لطف خداوند","desc":"عطاى تمام خواسته‌هاى انسان توسط خداوند","sura":14,"aya":34},{"topic":"خداوند","subtopic":"لطف خداوند","desc":"سرسبزشدن زمين توسط باران،  جلوه لطف و آگاهي خدا","sura":22,"aya":63},{"topic":"خداوند","subtopic":"لعنت خداوند","desc":"لعنت و عذاب خداوند در انتظار تهمت زنندگان به زنان پاكدامن و مؤمن","sura":24,"aya":23},{"topic":"خداوند","subtopic":"لوط نزد خداوند","desc":"منزلت واى لوط (ع) نزد خداوند","sura":37,"aya":134},{"topic":"خداوند","subtopic":"مالكيت خداوند","desc":"مالكيت مطلق خداوند بر همه موجودات آسمانها و زمين","sura":21,"aya":19},{"topic":"خداوند","subtopic":"مالكيت خداوند","desc":"مالكيت مطلق خداوند بر آسمانها و زمين","sura":24,"aya":64},{"topic":"خداوند","subtopic":"مالكيت خداوند","desc":"مالكيت مطلق خداوند بر آسمانها و زمين","sura":25,"aya":2},{"topic":"خداوند","subtopic":"مالكيت خداوند","desc":"مالكيت خداوند بر دنيا و آخرت","sura":92,"aya":13},{"topic":"خداوند","subtopic":"مالكيت خداوند","desc":"مالكيت خداوند بر جميع موجودات","sura":30,"aya":26},{"topic":"خداوند","subtopic":"مالكيت خداوند","desc":"مالكيت گسترده الهي بر جميع موجودات","sura":31,"aya":26},{"topic":"خداوند","subtopic":"مالكيت خداوند","desc":"مالكيت بي حد و مرز خداوند بر تمامي موجودات","sura":34,"aya":1},{"topic":"خداوند","subtopic":"مالكيت خداوند","desc":"انحصار مالكيت و تدبير آفرينش در خداوند","sura":35,"aya":13},{"topic":"خداوند","subtopic":"مالكيت خداوند","desc":"عظمت و بلندى مرتبت خداوند و مالكيت او بر جهان آفرينش","sura":42,"aya":4},{"topic":"خداوند","subtopic":"متكبر و خداوند","desc":"دورى متكبر و خودپسند از حب الهي","sura":31,"aya":18},{"topic":"خداوند","subtopic":"مجازات خداوند","desc":"تگرگ زيانبار مظهر قهر خداوند نسبت به اهالي بعضي مناطق","sura":24,"aya":43},{"topic":"خداوند","subtopic":"مجازاتهاى خداوند","desc":"بي تاثيرشدن مجازاتهاى تربيتي خداوند در بعضي از كافران","sura":23,"aya":76},{"topic":"خداوند","subtopic":"مجازاتهاى خداوند","desc":"مجازاتهاى تربيتي خداوند براى ايجاد حالت تواضع و تضرع","sura":23,"aya":76},{"topic":"خداوند","subtopic":"محبت خداوند","desc":"محروميت مستكبران از محبت خداوند","sura":16,"aya":23},{"topic":"خداوند","subtopic":"محبت خداوند","desc":"خيانت و ناسپاسي مشركان و محروميتشان از محبت خداوند","sura":22,"aya":38},{"topic":"خداوند","subtopic":"محضر خداوند","desc":"دعوت از صاحبان نفس مطمئن در قيامت به حضور شادمان در محضر خدا","sura":89,"aya":27},{"topic":"خداوند","subtopic":"محضر خداوند","desc":"دعوت از صاحبان نفس مطمئن در قيامت به حضور شادمان در محضر خدا","sura":89,"aya":30},{"topic":"خداوند","subtopic":"مخالفت با خداوند","desc":"سرانجام وخيم مخالفت با خداوند و پيامبران او","sura":35,"aya":26},{"topic":"خداوند","subtopic":"مداراى خداوند","desc":"مداراى خداوند در بازخواست و عذاب انسانها","sura":35,"aya":45},{"topic":"خداوند","subtopic":"مداراى خداوند","desc":"خطاكارى انسانها و مداراى خداوند","sura":35,"aya":45},{"topic":"خداوند","subtopic":"مداراى خداوند","desc":"مداراى خداوند در هدايت انسانها با وجود گمراهي آنان","sura":36,"aya":14},{"topic":"خداوند","subtopic":"مداراى خداوند","desc":"مداراى خداوند با منكرين و ملحدين در زندگي دنيا","sura":41,"aya":45},{"topic":"خداوند","subtopic":"مراقبت خداوند","desc":"مراقبت دائمي خداوند بر هر چيز","sura":33,"aya":52},{"topic":"خداوند","subtopic":"مزد از سوى خداوند","desc":"طلب مزد  فقط از خداوند","sura":26,"aya":109},{"topic":"خداوند","subtopic":"مشاهده خداوند","desc":"مشاهده خداوند يا فرشتگان شرط پيشنهادى مشركان براى تصديق پيامبر اكرم","sura":25,"aya":21},{"topic":"خداوند","subtopic":"مشاهده خداوند","desc":"استكبار و طغيان مشركان درپي درخواست مشاهده خدا و فرشتگان","sura":25,"aya":21},{"topic":"خداوند","subtopic":"مشتاقان خداوند","desc":"تاثير كلام پيامبر (ص) در دلهاى مشتاق به خداوند","sura":36,"aya":11},{"topic":"خداوند","subtopic":"مشركان دربرابر خداوند","desc":"اعتراف مشركان به آفرينش آسمانها و زمين توسط خداوند","sura":39,"aya":38},{"topic":"خداوند","subtopic":"مشركان و خداوند","desc":"اعتراف مشركان به انتساب و تدبير به خداوند","sura":29,"aya":61},{"topic":"خداوند","subtopic":"مشيت خداوند","desc":"مشروط بودن عفو الهي به مشيت او","sura":4,"aya":48},{"topic":"خداوند","subtopic":"مشيت خداوند","desc":"برترى يافتن برخي مردم بر برخي ديگر در دنيا برحسب مشيت خداوند","sura":17,"aya":21},{"topic":"خداوند","subtopic":"مشيت خداوند","desc":"تزكيه آدمي و پاک گرديدن او در گرو مشيت حكيمانه خداوند","sura":24,"aya":21},{"topic":"خداوند","subtopic":"مشيت خداوند","desc":"آسيب ديدن از بارش تگرگ بر اساس مشيت حكيمانه خداوند","sura":24,"aya":43},{"topic":"خداوند","subtopic":"مشيت خداوند","desc":"هدايتيافتن افراد در گرو مشيت خداوند","sura":24,"aya":46},{"topic":"خداوند","subtopic":"مشيت خداوند","desc":"نابودى انسانها براثر غرق شدن در درياها به مشيت خداوند","sura":36,"aya":43},{"topic":"خداوند","subtopic":"مشيت خداوند","desc":"مشيت خداوند براى زيستن آدمي بمدت معين","sura":40,"aya":67},{"topic":"خداوند","subtopic":"مشيت خداوند","desc":"تقدير تمامي شئونات زندگي انسان ازسوى خدا","sura":53,"aya":43},{"topic":"خداوند","subtopic":"مشيت خداوند","desc":"قرارداشتن مرگ و زندگي انسان به مشيت و قدرت خداوند","sura":53,"aya":44},{"topic":"خداوند","subtopic":"معبودى غير از خداوند","desc":"نفي هرگونه معبودى كه حامي كافران باشد","sura":21,"aya":43},{"topic":"خداوند","subtopic":"معرفت به خداوند","desc":"ادراک حقيقت قرآن درپرتو معرفت به خداوند و آيات او","sura":34,"aya":6},{"topic":"خداوند","subtopic":"معرفت به خداوند","desc":"اهميت تهذيب و تصحيح معرفت نسبت به خداوند","sura":39,"aya":11},{"topic":"خداوند","subtopic":"مغفرت خداوند","desc":"آمرزش خداوند درباره تمام گناهان و خطاها","sura":39,"aya":53},{"topic":"خداوند","subtopic":"مغفرت خداوند","desc":"غفران و رحمت الهي، زمينه دلبستگي به خداوند","sura":39,"aya":53},{"topic":"خداوند","subtopic":"مكر خداوند","desc":"مكر ورزيدن كفار قريش و مكر خداوند","sura":8,"aya":30},{"topic":"خداوند","subtopic":"مكر خداوند","desc":"خداوند برترين مكركنندگان","sura":8,"aya":30},{"topic":"خداوند","subtopic":"ملاقات با خداوند","desc":"قيامت، روز ملاقات با خداوند و بروز تمامي حقايق","sura":40,"aya":15},{"topic":"خداوند","subtopic":"مناجات خداوند","desc":"دوزخي شدن آدمي درپي سرپيچي از پرستش و مناجات خداوند","sura":40,"aya":60},{"topic":"خداوند","subtopic":"منت خداوند","desc":"منت خداوند بر موسي در نجات وى از چنگال فرعونيان","sura":20,"aya":39},{"topic":"خداوند","subtopic":"مهرباني خداوند","desc":"عزت و مهرباني خداوند","sura":26,"aya":9},{"topic":"خداوند","subtopic":"مهرباني خداوند","desc":"تجلي عزت خداوند در نابودى تمدنهاى سركش و مهرباني او در نجات دينداران","sura":26,"aya":175},{"topic":"خداوند","subtopic":"مهرباني خداوند","desc":"مهرباني خداوند به مومنان","sura":33,"aya":43},{"topic":"خداوند","subtopic":"مهلت خداوند","desc":"مهلت خداوند به گنهكاران و تاخير عذابشان تا زمان مرگ","sura":16,"aya":61},{"topic":"خداوند","subtopic":"مهلت دادن خداوند","desc":"مهلت خداوند به كفار و كيفر شديد او بعداز انقضاء مهلت","sura":13,"aya":32},{"topic":"خداوند","subtopic":"مواهب خداوند","desc":"فرزند صالح، موهبت خداوند بر آدمي","sura":37,"aya":101},{"topic":"خداوند","subtopic":"موسي (ع) نزد خداوند","desc":"اخبار خداوند به ايمني موسي (ع) نزد وى","sura":28,"aya":31},{"topic":"خداوند","subtopic":"موسي (ع) و خداوند","desc":"پيمان موسي با خدا مبني بر عدم پشتيباني از مجرمان","sura":28,"aya":17},{"topic":"خداوند","subtopic":"موسي (ع) و خداوند","desc":"درخواست موسي از خداوند براى رهائي از چنگال ظالمان","sura":28,"aya":21},{"topic":"خداوند","subtopic":"موسي (ع) و خداوند","desc":"استدعاى موسي (ع) از خداوند براى رسيدن به راه درست","sura":28,"aya":22},{"topic":"خداوند","subtopic":"موسي (ع) و خداوند","desc":"توجه موسي (ع) به خداوند در حوادث زندگي","sura":28,"aya":24},{"topic":"خداوند","subtopic":"موسي (ع) و خداوند","desc":"درخواست موسي (ع) از خداوند براى فرستادن برادرش هارون به همراه وى","sura":28,"aya":34},{"topic":"خداوند","subtopic":"موسي (ع) و خداوند","desc":"اجابت درخواست موسي (ع) مبني بر همراهي هارون با وى","sura":28,"aya":35},{"topic":"خداوند","subtopic":"موسي نزد خداوند","desc":"مقام و منزلت واى موسي (ع) نزد خداوند","sura":33,"aya":69},{"topic":"خداوند","subtopic":"موسي و خداوند","desc":"پناه و توكل موسي (ع) به خداوند در برابر متكبران و منكران قيامت","sura":40,"aya":27},{"topic":"خداوند","subtopic":"ميثاق با خداوند","desc":"ميثاق آدمي با خداوند قبل از امتحان و عهدشكني پس از آن","sura":35,"aya":42},{"topic":"خداوند","subtopic":"ميثاق خداوند","desc":"عهد و ميثاق خاص خداوند با انبياء","sura":33,"aya":7},{"topic":"خداوند","subtopic":"ميثاق خداوند","desc":"ميثاق و پيمان استوار خداوند بانوح (ع) و ابراهيم (ع) و موسي (ع) و عيسي (ع) و پيامبر (ص)","sura":33,"aya":7},{"topic":"خداوند","subtopic":"ميراندن بوسيله خداوند","desc":"زنده گردانيدن و ميرانيدن همه موجودات به تدبير و مشيت خداوند","sura":40,"aya":67},{"topic":"خداوند","subtopic":"ميهماني خداوند","desc":"ميهماني احسان خداوند مهربان براى مؤمنان","sura":41,"aya":31},{"topic":"خداوند","subtopic":"نااميدى جزاز خداوند","desc":"نااميدى هرگونه مدد و ياورى در قيامت جز ازسوى خداوند","sura":40,"aya":33},{"topic":"خداوند","subtopic":"ناخشنودى خداوند","desc":"مخالفت خداوند با خشنودى مومنان از منافقان","sura":9,"aya":96},{"topic":"خداوند","subtopic":"ناداني درباره خداوند","desc":"پندار واهي جاهلان در مورد برقرارى رابطه خويشاوندى بين خدا و جن","sura":37,"aya":158},{"topic":"خداوند","subtopic":"ناسپاسي در برابر خداوند","desc":"سرانجام تلخ ناسپاسي دربرابر خداوند","sura":35,"aya":36},{"topic":"خداوند","subtopic":"نام خداوند","desc":"افتتاح نامه سليمان با نام خداى بخشنده مهربان","sura":27,"aya":30},{"topic":"خداوند","subtopic":"نام خداوند","desc":"دلتنگ شدن كافران از شنيدن نام خدا و ياد او","sura":39,"aya":45},{"topic":"خداوند","subtopic":"نشانه هاى خداوند","desc":"تدبير در كار آفرينش و ارائه نشانه‌هاى واضح به اميد ايمان آوردن بندگان","sura":13,"aya":2},{"topic":"خداوند","subtopic":"نشانه هاى خداوند","desc":"نشانه‌هاى خداوند براى انديشمندان در ميوه درخت خرما و انگور","sura":16,"aya":67},{"topic":"خداوند","subtopic":"نشانه هاى خداوند","desc":"وجود نشانه‌هايي در خلقت انسان و ساير جانداران براى اهل يقين","sura":45,"aya":4},{"topic":"خداوند","subtopic":"نصرت خداوند","desc":"پيروز گردانيدن نوح و هلاكت تكذيب‌كنندگان وى در دريا","sura":21,"aya":77},{"topic":"خداوند","subtopic":"نصرت خداوند","desc":"وعده نصرت خداوند براى آنانكه جنگ بر آنها تحميل مي‌شود","sura":22,"aya":39},{"topic":"خداوند","subtopic":"نصرت خداوند","desc":"وعده نصرت خداوند براى ياوران دين خدا","sura":22,"aya":40},{"topic":"خداوند","subtopic":"نظارت خداوند","desc":"آدمي در هرحال، شب و روز، تحت نظر خداوند","sura":13,"aya":10},{"topic":"خداوند","subtopic":"نعم خداوند","desc":"لزوم سپاسگزارى از خداوند به پاس ثمرات گياهان و ميوه‌هاى درختان و تغذيه آدمي","sura":36,"aya":35},{"topic":"خداوند","subtopic":"نعمت خداوند","desc":"خشنودى شهيدان بر نعمت و فضل خداوند","sura":3,"aya":171},{"topic":"خداوند","subtopic":"نعمت خداوند","desc":"نعمت خداوند در آفرينش چهارپايان براى آدمي","sura":40,"aya":79},{"topic":"خداوند","subtopic":"نعمتهاى خداوند","desc":"غير قابل شمارش بودن نعمتهاى الهي","sura":16,"aya":18}]