[{"topic":"هود","subtopic":"اعراض از هود (ع)","desc":"رويگرداني مردم از دعوت هود به پارسائي و پيروى خداوند و ديندارى","sura":26,"aya":126},{"topic":"هود","subtopic":"اعراض از هود (ع)","desc":"رويگرداني مردم از دعوت هود به پارسائي و پيروى خداوند و ديندارى","sura":26,"aya":128},{"topic":"هود","subtopic":"انتقاد هود","desc":"انتقاد هود از قوم خود به علت بناى ساختمان بر بلندى براى منظورى بيهوده","sura":26,"aya":129},{"topic":"هود","subtopic":"انتقاد هود","desc":"انتقاد هود از قوم خود به علت بناى كاخها به اميد جاودانه زيستن در آنها","sura":26,"aya":130},{"topic":"هود","subtopic":"انتقاد هود","desc":"انتقاد هود از قوم خود به علت افراط آنان در خشم","sura":46,"aya":21},{"topic":"هود","subtopic":"انذار هود","desc":"تهديد قوم عاد توسط هود به نزول عذاب الهي در صورت رد دعوت وى","sura":11,"aya":53},{"topic":"هود","subtopic":"باورآوردن به هود","desc":"باورنياوردن قوم عاد به هود","sura":26,"aya":136},{"topic":"هود","subtopic":"پاسخ به هود","desc":"پاسخ قوم هود به دعوت او به پرواى از خدا","sura":7,"aya":65},{"topic":"هود","subtopic":"پيامبرى هود","desc":"ارسال هود به‌سوى قوم عاد","sura":11,"aya":50},{"topic":"هود","subtopic":"پيامبرى هود","desc":"فرستادن حضرت هود بسوى قوم عاد","sura":7,"aya":70},{"topic":"هود","subtopic":"تكذيب هود","desc":"تكذيب هود ازسوى قوم عاد","sura":22,"aya":42},{"topic":"هود","subtopic":"تكذيب هود","desc":"تكذيب نوح، هود و صالح از سوى قومشان","sura":26,"aya":138},{"topic":"هود","subtopic":"تكذيب هود","desc":"تكذيب سخن هود از سوى قوم او مبني بر فرارسيدن عذاب برآنان","sura":46,"aya":22},{"topic":"هود","subtopic":"تكذيب هود","desc":"تكذيب نبوت هود ازسوى قوم عاد","sura":11,"aya":56},{"topic":"هود","subtopic":"توكل هود","desc":"توكل هود بر خداوند درمقابل توطئه‌هاى مشركان","sura":11,"aya":55},{"topic":"هود","subtopic":"حقانيت هود","desc":"يقين و اطمينان هود به حقانيت دعوت خود","sura":11,"aya":53},{"topic":"هود","subtopic":"دعوت هود","desc":"واكنش قوم عاد درمقابل دعوت هود به توحيد","sura":11,"aya":53},{"topic":"هود","subtopic":"دعوت هود","desc":"رد دعوت هود از سوى قوم او","sura":26,"aya":123},{"topic":"هود","subtopic":"دعوت هود","desc":"رويگرداني مردم از دعوت هود به پارسائي و پيروى خداوند و ديندارى","sura":26,"aya":124},{"topic":"هود","subtopic":"دعوت هود","desc":"دعوت قوم عاد از سوى هود به تقوا","sura":26,"aya":126},{"topic":"هود","subtopic":"دعوت هود","desc":"رويگرداني مردم از دعوت هود به پارسائي و پيروى خداوند و ديندارى","sura":26,"aya":126},{"topic":"هود","subtopic":"دعوت هود","desc":"دعوت قوم عاد از سوى هود به فرمان بردن از او و پرواى از خدا","sura":26,"aya":127},{"topic":"هود","subtopic":"دعوت هود","desc":"بي‌مزد و اجربودن دعوت هود به‌سوى خدا","sura":26,"aya":127},{"topic":"هود","subtopic":"دعوت هود","desc":"اخلاص هود در دعوت بسوى خدا","sura":26,"aya":136},{"topic":"هود","subtopic":"دعوت هود","desc":"پاسخ قوم هود به دعوت او به پرواى از خدا","sura":7,"aya":65},{"topic":"هود","subtopic":"رسالت هود","desc":"دعوت مردم به توحيد ازسوى هود","sura":26,"aya":139},{"topic":"هود","subtopic":"سرپيچي از هود","desc":"ضرورت عبرت آموزى از هلاكت قوم عاد درپي سرپيچي از هود و انكار قيامت","sura":46,"aya":22},{"topic":"هود","subtopic":"عاديان و هود","desc":"پاسخ قوم عاد به تهديد حضرت هود","sura":11,"aya":89},{"topic":"هود","subtopic":"قوم هود","desc":"يادآورى عاقبت قوم نوح و هود و صالح و لوط براى عبرت قوم مدين","sura":26,"aya":127},{"topic":"هود","subtopic":"مزد نخواستن هود","desc":"بي‌مزد و اجربودن دعوت هود به‌سوى خدا","sura":46,"aya":23},{"topic":"هود","subtopic":"مسئوليت هود","desc":"مسئوليت هود در ابلاغ رسالت و انذار مردم","sura":11,"aya":53},{"topic":"هود","subtopic":"مشركان و هود","desc":"واكنش قوم عاد درمقابل دعوت هود به توحيد","sura":11,"aya":54},{"topic":"هود","subtopic":"مشركان و هود","desc":"پندار مشركان درمورد آسيب رساني بتها به هود","sura":11,"aya":54},{"topic":"هود","subtopic":"مشركان و هود","desc":"اتهام جنون به هود ازسوى مشركان","sura":46,"aya":22},{"topic":"هود","subtopic":"نبوت هود","desc":"تكذيب نبوت هود ازسوى قوم عاد","sura":7,"aya":72},{"topic":"هود","subtopic":"نجات هود","desc":"نجات هود و پيروانش از عذاب الهي و نابودى مشركان عاد","sura":11,"aya":58},{"topic":"هود","subtopic":"نجات هود","desc":"نجات هود و پيروان مؤمن او از عذاب شديد","sura":11,"aya":55},{"topic":"هود","subtopic":"هود و بتان","desc":"اثبات ناتواني بتها ازسوى هود با خواندن آنها به مبارزه با خود","sura":11,"aya":53},{"topic":"هود","subtopic":"هود و عاد","desc":"رد دعوت هود از سوى قوم او","sura":11,"aya":53},{"topic":"هود","subtopic":"هود و عاد","desc":"باورنياوردن قوم عاد به هود","sura":11,"aya":57},{"topic":"هود","subtopic":"هود و عاد","desc":"ابلاغ رسالت و اتمام حجت هود بر قوم عاد","sura":26,"aya":125},{"topic":"هود","subtopic":"هود و عاد","desc":"هود، فرستاده‌اى امين به سوى قوم عاد","sura":26,"aya":126},{"topic":"هود","subtopic":"هود و عاد","desc":"دعوت قوم عاد از سوى هود به فرمان بردن از او و پرواى از خدا","sura":7,"aya":70},{"topic":"هود","subtopic":"هود و قوم او","desc":"رد دعوت هود از سوى قوم او","sura":7,"aya":71},{"topic":"هود","subtopic":"هود و قوم او","desc":"رد استدلال قوم عاد از سوى هود","sura":26,"aya":128},{"topic":"هود","subtopic":"هود و قوم او","desc":"انتقاد هود از قوم خود به علت بناى ساختمان بر بلندى براى منظورى بيهوده","sura":26,"aya":129},{"topic":"هود","subtopic":"هود و قوم او","desc":"انتقاد هود از قوم خود به علت بناى كاخها به اميد جاودانه زيستن در آنها","sura":26,"aya":129},{"topic":"هود","subtopic":"هود و قوم او","desc":"اعتراض هود به قوم خود به علت فراموش كردن سراى آخرت","sura":26,"aya":130},{"topic":"هود","subtopic":"هود و قوم او","desc":"انتقاد هود از قوم خود به علت افراط آنان در خشم","sura":26,"aya":131},{"topic":"هود","subtopic":"هود و قوم او","desc":"توصيه هود به قوم خود براى پرواداشتن از خدا و فرمان بردن از هود","sura":26,"aya":136},{"topic":"هود","subtopic":"هود و قوم او","desc":"پاسخ قوم هود به دعوت او به پرواى از خدا","sura":26,"aya":138},{"topic":"هود","subtopic":"هود و قوم او","desc":"تكذيب سخن هود از سوى قوم او مبني بر فرارسيدن عذاب برآنان","sura":46,"aya":21},{"topic":"هود","subtopic":"هود و قوم او","desc":"تهديد قوم عاد توسط هود به نزول عذاب الهي در صورت رد دعوت وى","sura":46,"aya":23},{"topic":"هود","subtopic":"هود و قوم او","desc":"پاسخ هود به عاديان و درخواست آنان مبني بر نزول عذاب","sura":11,"aya":54},{"topic":"هود","subtopic":"هود و مشركان","desc":"اعلام بيزارى و تنفر هود از بتهاى مشركان","sura":11,"aya":56},{"topic":"هود","subtopic":"هود و مشركان","desc":"توكل هود بر خداوند درمقابل توطئه‌هاى مشركان","sura":11,"aya":57},{"topic":"هود","subtopic":"هود و مشركان","desc":"تهديد مشركان به عذاب الهي ازسوى هود","sura":11,"aya":55},{"topic":"هود","subtopic":"يقين هود","desc":"يقين و اطمينان هود به حقانيت دعوت خود","sura":75,"aya":5},{"topic":"هوس","subtopic":"آثار هوس","desc":"نقش هوا و هوس در پرستش بتها و معبودهاى دروغين","sura":28,"aya":50},{"topic":"هوس","subtopic":"پيروان هوس","desc":"پيروى منكران تورات و قرآن و عاجزان از پاسخ به تحدى رسول خدا (ص) از هوا و هوس خويش","sura":28,"aya":50},{"topic":"هوس","subtopic":"پيروان هوس","desc":"گمراهي پيروان هوا و هوس","sura":4,"aya":135},{"topic":"هوس","subtopic":"پيروى از هوس","desc":"پيروى از هوا و هوس، مهمترين مانع اجراى عدالت","sura":4,"aya":135},{"topic":"هوس","subtopic":"پيروى از هوس","desc":"پيروى از هوس، عامل عدول از حق","sura":5,"aya":30},{"topic":"هوس","subtopic":"پيروى از هوس","desc":"پيروى قابيل از هواى نفس و دست گشودن او به قتل هابيل","sura":5,"aya":48},{"topic":"هوس","subtopic":"پيروى از هوس","desc":"نهي پيامبر (ص) از پيروى خواهشها و هوسهاى مردم","sura":5,"aya":49},{"topic":"هوس","subtopic":"پيروى از هوس","desc":"منع پيامبر (ص) از پيروى از هوسهاى كساني كه براى داورى نزد او مي‌آيند","sura":6,"aya":119},{"topic":"هوس","subtopic":"پيروى از هوس","desc":"گمراهي بسيارى از مردم دراثر پيروى از هواوهوس","sura":6,"aya":150},{"topic":"هوس","subtopic":"پيروى از هوس","desc":"نهي از پيروى از هوا و هوس مشركان","sura":30,"aya":29},{"topic":"هوس","subtopic":"پيروى از هوس","desc":"پيروى جاهلانه ستمگران از هوسهاى خويش","sura":30,"aya":29},{"topic":"هوس","subtopic":"ستمگران و هوس","desc":"پيروى جاهلانه ستمگران از هوسهاى خويش","sura":15,"aya":75},{"topic":"هوسراني","subtopic":"آثار هوسراني","desc":"ميل به گناه و هواپرستي از عوامل مهم تلاش كافران و مجرمان در انكار معاد","sura":40,"aya":75},{"topic":"هوسراني","subtopic":"عواقب هوسراني","desc":"سرانجام وخيم آدمي درپي هوسراني و سرگرمي بدون هدف در دنيا","sura":40,"aya":75},{"topic":"هوسراني","subtopic":"عواقب هوسراني","desc":"سرنوشت وخيم آدمي درپي هوسراني و بي‌اعتنايي به شريعت و خداوند","sura":30,"aya":29},{"topic":"هوسراني","subtopic":"گمراهي در پي هوسراني","desc":"گمراهي انسان در پي هوسراني و خطا","sura":54,"aya":3},{"topic":"هوسراني","subtopic":"هوسراني كافران","desc":"پيروى كفار از هوى و هوس خود در انكار معجزات پيامبر","sura":68,"aya":38},{"topic":"هوسراني","subtopic":"هوسراني كافران","desc":"پيروى كفار معاند از هوى و هوس و اميال نفساني خود","sura":6,"aya":56},{"topic":"هوشياران","subtopic":"عبرت گيرى هوشياران","desc":"عبرت آموزبودن سرگذشت قوم لوط براى هوشياران","sura":54,"aya":7},{"topic":"هولناكي","subtopic":"هولناكي قيامت","desc":"هولناكي صحنه قيامت براى كافران و مشركان","sura":87,"aya":1},{"topic":"هولناكي","subtopic":"هولناكي قيامت","desc":"بازگويي خبر هولناک قيامت براى پيامبر","sura":21,"aya":7},{"topic":"هويت","subtopic":"هويت انبياء","desc":"انبياء، مرداني عادى از ميان مردم","sura":21,"aya":8},{"topic":"هويت","subtopic":"هويت انبياء","desc":"انبياء مردماني عادى با غرائز انساني و نياز به خورد و خوراک","sura":21,"aya":8},{"topic":"هويت","subtopic":"هويت انبياء","desc":"مرگ و حيات عادى انبياء در دنيا","sura":25,"aya":20},{"topic":"هويت","subtopic":"هويت انبياء","desc":"همه انبياء انسانهايي عادى با نيازهاى بشرى","sura":23,"aya":32},{"topic":"هويت","subtopic":"هويت پيامبران","desc":"رسولان الهي افرادى عادى ازميان مردم","sura":21,"aya":26},{"topic":"هويت","subtopic":"هويت فرشتگان","desc":"فرشتگان، بندگان ارجمند خدا نه فرزندان وى","sura":72,"aya":15},{"topic":"هيزم","subtopic":"هيزم آتش","desc":"كافران، آتشگيره و هيزم آتش دوزخ","sura":21,"aya":98},{"topic":"هيزم","subtopic":"هيزم جهنم","desc":"مشركان و معبودهايشان، هيزم دوزخ","sura":66,"aya":6},{"topic":"هيزم","subtopic":"هيزم دوزخ","desc":"سنگها و انسانهاى كافر و گنهكار، هيزمهاى دوزخ","sura":21,"aya":96},{"topic":"هيزم","subtopic":"هيزمهاى دوزخ","desc":"كافران و ظالمان از جن و انس هيزمهاى آتش دوزخ","sura":3,"aya":10},{"topic":"وابستگي","subtopic":"وابستگي انسان","desc":"فقر محض انسان و وابستگي كامل او به خداوند","sura":56,"aya":71},{"topic":"وابستگي","subtopic":"وابستگي انسان","desc":"وابستگي و نياز انسان به خدا در تمام شئونات زندگي خود","sura":56,"aya":71},{"topic":"وابستگي","subtopic":"وابستگي انسان","desc":"نقش علم انسان به ناتواني و عدم استقلال خود در خداشناسي","sura":4,"aya":123},{"topic":"وابستگي","subtopic":"وابستگي به اديان","desc":"بي اثربودن وابستگيهاى ظاهرى به اديان در سعادت انسان","sura":3,"aya":144},{"topic":"وابستگي","subtopic":"وابستگي به پيامبر","desc":"هشدار به مسلمانان نسبت به فردپرستي و وابسته كردن ايمان خود به پيامبر (ص)","sura":73,"aya":8},{"topic":"وابستگي","subtopic":"وابستگي به خدا","desc":"دعوت پيامبر به تداوم ياد خدا و نعمتهاى او و بريدن از خلق","sura":35,"aya":16},{"topic":"وابستگي","subtopic":"وابستگي به خداوند","desc":"وابسته بودن آدمي به خداوند در تمامي جهات دليل حاجت آدمي به خداوند","sura":2,"aya":185},{"topic":"واجب","subtopic":"روزه غير واجب","desc":"عدم وجوب روزه ماه رمضان بر بيمار و مسافر","sura":2,"aya":184},{"topic":"واجب","subtopic":"روزه واجب","desc":"وجوب قضاى روزه بر بيماران و مسافران","sura":2,"aya":196},{"topic":"واجب","subtopic":"روزه واجب","desc":"وجوب روزه در صورت عدم توانايي بر قرباني در حب","sura":2,"aya":185},{"topic":"واجب","subtopic":"واجب موسع","desc":"وسعت زمان قضاى روزه ماه رمضان","sura":23,"aya":52}]